acdh_django_handle-0.1.1.dist-info/DESCRIPTION.rst
acdh_django_handle-0.1.1.dist-info/METADATA
acdh_django_handle-0.1.1.dist-info/RECORD
acdh_django_handle-0.1.1.dist-info/WHEEL
acdh_django_handle-0.1.1.dist-info/metadata.json
acdh_django_handle-0.1.1.dist-info/top_level.txt
handle/__init__.py
handle/admin.py
handle/apps.py
handle/models.py
handle/urls.py
handle/utils.py
handle/views.py
handle/management/__init__.py
handle/management/commands/__init__.py
handle/management/commands/create_handles.py
handle/migrations/0001_initial.py
handle/migrations/__init__.py
handle/static/css/handle.css
handle/static/js/handle.js
handle/templates/handle/base.html
