Metadata-Version: 2.0
Name: acdh-django-handle
Version: 0.1.1
Summary: A django app to create and manage handle-pids
Home-page: https://github.com/acdh-oeaw/acdh-django-handle
Author: Peter Andorfer
Author-email: peter.andorfer@oeaw.ac.at
License: MIT
Keywords: acdh-django-handle
Platform: UNKNOWN
Classifier: Development Status :: 3 - Alpha
Classifier: Framework :: Django :: 2.0
Classifier: Intended Audience :: Developers
Classifier: License :: OSI Approved :: BSD License
Classifier: Natural Language :: English
Classifier: Programming Language :: Python :: 2
Classifier: Programming Language :: Python :: 2.7
Classifier: Programming Language :: Python :: 3
Classifier: Programming Language :: Python :: 3.4
Classifier: Programming Language :: Python :: 3.5
Classifier: Programming Language :: Python :: 3.6
Requires-Dist: requests
